{
  "Algeria": {
    "san-francisco": 23.15,
    "vancouver": 23.14,
    "new-york": 18.7,
    "philadelphia": 18.68,
    "houston": 18.67,
    "boston": 16.6,
    "guadalajara": 16.59,
    "dallas": 16.56,
    "seattle": 14.77,
    "los-angeles": 14.72,
    "kansas-city": 14.59,
    "toronto": 14.54,
    "miami": 14.53,
    "atlanta": 14.53,
    "monterrey": 14.34,
    "mexico-city": 4.2
  },
  "Argentina": {
    "houston": 24.16,
    "philadelphia": 22.8,
    "new-york": 22.74,
    "dallas": 22.1,
    "miami": 21.86,
    "atlanta": 21.86,
    "boston": 21.63,
    "toronto": 17.79,
    "kansas-city": 17.78,
    "guadalajara": 12.61,
    "san-francisco": 9.41,
    "los-angeles": 9.29,
    "seattle": 9.29,
    "vancouver": 9.29,
    "mexico-city": 6.36,
    "monterrey": 6.31
  },
  "Australia": {
    "san-francisco": 22.73,
    "vancouver": 22.46,
    "houston": 19.17,
    "new-york": 18.72,
    "philadelphia": 18.69,
    "dallas": 17.18,
    "boston": 16.62,
    "guadalajara": 16.34,
    "kansas-city": 14.99,
    "miami": 14.76,
    "atlanta": 14.76,
    "toronto": 14.61,
    "los-angeles": 14.39,
    "seattle": 14.33,
    "monterrey": 14.25,
    "mexico-city": 4.33
  },
  "Austria": {
    "atlanta": 22.31,
    "san-francisco": 20.67,
    "houston": 19.82,
    "new-york": 19.53,
    "philadelphia": 19.5,
    "dallas": 17.55,
    "boston": 17.34,
    "miami": 15.3,
    "toronto": 15.29,
    "kansas-city": 15.21,
    "los-angeles": 13.86,
    "vancouver": 13.71,
    "seattle": 13.71,
    "monterrey": 13.7,
    "mexico-city": 11.43,
    "guadalajara": 8.83
  },
  "Belgium": {
    "philadelphia": 26.73,
    "new-york": 26.67,
    "houston": 25.92,
    "dallas": 22.48,
    "boston": 22.44,
    "kansas-city": 20.91,
    "toronto": 20.86,
    "miami": 17.52,
    "atlanta": 17.52,
    "guadalajara": 10.03,
    "monterrey": 9.94,
    "san-francisco": 7.55,
    "los-angeles": 7.43,
    "seattle": 7.43,
    "vancouver": 7.43,
    "mexico-city": 5.05
  },
  "Brazil": {
    "new-york": 26.76,
    "philadelphia": 26.67,
    "houston": 25.71,
    "boston": 22.75,
    "dallas": 22.16,
    "toronto": 20.64,
    "kansas-city": 20.61,
    "miami": 17.67,
    "atlanta": 17.67,
    "guadalajara": 10.01,
    "monterrey": 9.89,
    "los-angeles": 7.6,
    "seattle": 7.6,
    "vancouver": 7.6,
    "san-francisco": 7.43,
    "mexico-city": 5.01
  },
  "Canada": {
    "toronto": 100.0,
    "vancouver": 100.0
  },
  "Cape Verde": {
    "san-francisco": 28.21,
    "atlanta": 24.3,
    "vancouver": 17.11,
    "seattle": 17.11,
    "monterrey": 16.99,
    "los-angeles": 16.61,
    "philadelphia": 16.5,
    "houston": 16.47,
    "new-york": 16.47,
    "mexico-city": 15.05,
    "boston": 14.6,
    "dallas": 14.55,
    "miami": 12.83,
    "toronto": 12.8,
    "kansas-city": 12.78,
    "guadalajara": 7.3
  },
  "Colombia": {
    "san-francisco": 26.79,
    "vancouver": 26.62,
    "guadalajara": 17.84,
    "new-york": 17.31,
    "philadelphia": 17.31,
    "houston": 17.01,
    "monterrey": 16.19,
    "los-angeles": 16.14,
    "seattle": 16.08,
    "dallas": 15.49,
    "boston": 15.37,
    "toronto": 13.55,
    "kansas-city": 13.48,
    "miami": 13.13,
    "atlanta": 13.13,
    "mexico-city": 3.69
  },
  "Croatia": {
    "toronto": 22.71,
    "philadelphia": 19.68,
    "new-york": 19.67,
    "houston": 19.38,
    "dallas": 17.49,
    "boston": 17.45,
    "guadalajara": 15.85,
    "kansas-city": 15.28,
    "miami": 15.16,
    "atlanta": 15.16,
    "vancouver": 13.85,
    "los-angeles": 13.7,
    "seattle": 13.7,
    "mexico-city": 11.44,
    "san-francisco": 6.71,
    "monterrey": 6.3
  },
  "Curacao": {
    "new-york": 25.11,
    "philadelphia": 24.95,
    "houston": 24.87,
    "boston": 22.54,
    "dallas": 22.09,
    "miami": 19.65,
    "atlanta": 19.65,
    "toronto": 19.44,
    "kansas-city": 19.17,
    "guadalajara": 11.23,
    "san-francisco": 8.33,
    "los-angeles": 8.25,
    "seattle": 8.25,
    "vancouver": 8.25,
    "monterrey": 8.2,
    "mexico-city": 5.6
  },
  "Ecuador": {
    "san-francisco": 26.63,
    "atlanta": 23.87,
    "houston": 17.25,
    "philadelphia": 17.17,
    "new-york": 17.12,
    "monterrey": 16.34,
    "vancouver": 16.29,
    "seattle": 16.29,
    "los-angeles": 16.06,
    "dallas": 15.18,
    "boston": 15.11,
    "mexico-city": 14.29,
    "toronto": 13.36,
    "kansas-city": 13.33,
    "miami": 13.32,
    "guadalajara": 7.62
  },
  "Egypt": {
    "san-francisco": 23.05,
    "vancouver": 23.0,
    "houston": 18.66,
    "philadelphia": 18.66,
    "new-york": 18.66,
    "guadalajara": 16.82,
    "dallas": 16.73,
    "boston": 16.54,
    "los-angeles": 14.75,
    "toronto": 14.7,
    "monterrey": 14.66,
    "kansas-city": 14.51,
    "miami": 14.48,
    "atlanta": 14.48,
    "seattle": 14.45,
    "mexico-city": 4.13
  },
  "England": {
    "houston": 23.89,
    "philadelphia": 23.1,
    "new-york": 23.06,
    "dallas": 22.02,
    "boston": 21.94,
    "miami": 21.69,
    "atlanta": 21.69,
    "toronto": 17.95,
    "kansas-city": 17.77,
    "guadalajara": 12.37,
    "san-francisco": 9.35,
    "los-angeles": 9.33,
    "seattle": 9.33,
    "vancouver": 9.33,
    "monterrey": 6.29,
    "mexico-city": 6.18
  },
  "France": {
    "houston": 24.08,
    "new-york": 22.82,
    "philadelphia": 22.8,
    "dallas": 21.91,
    "miami": 21.91,
    "atlanta": 21.91,
    "boston": 21.77,
    "toronto": 17.72,
    "kansas-city": 17.66,
    "guadalajara": 12.61,
    "los-angeles": 9.36,
    "seattle": 9.36,
    "vancouver": 9.36,
    "san-francisco": 9.34,
    "mexico-city": 6.31,
    "monterrey": 6.29
  },
  "Germany": {
    "new-york": 26.64,
    "philadelphia": 26.64,
    "houston": 25.84,
    "dallas": 22.73,
    "boston": 22.49,
    "kansas-city": 20.96,
    "toronto": 20.85,
    "miami": 17.38,
    "atlanta": 17.38,
    "monterrey": 10.14,
    "guadalajara": 9.93,
    "san-francisco": 7.55,
    "los-angeles": 7.43,
    "seattle": 7.43,
    "vancouver": 7.43,
    "mexico-city": 5.01
  },
  "Ghana": {
    "san-francisco": 28.42,
    "atlanta": 24.24,
    "los-angeles": 17.03,
    "monterrey": 16.92,
    "vancouver": 16.7,
    "seattle": 16.7,
    "houston": 16.51,
    "philadelphia": 16.41,
    "new-york": 16.39,
    "mexico-city": 15.07,
    "dallas": 14.58,
    "boston": 14.56,
    "kansas-city": 12.84,
    "miami": 12.84,
    "toronto": 12.66,
    "guadalajara": 7.32
  },
  "Haiti": {
    "houston": 24.87,
    "new-york": 24.86,
    "philadelphia": 24.84,
    "boston": 22.13,
    "dallas": 22.09,
    "miami": 19.48,
    "atlanta": 19.48,
    "kansas-city": 19.36,
    "toronto": 19.31,
    "guadalajara": 11.16,
    "los-angeles": 8.55,
    "seattle": 8.55,
    "vancouver": 8.55,
    "san-francisco": 8.44,
    "monterrey": 8.14,
    "mexico-city": 5.58
  },
  "Inter Path 1": {
    "houston": 25.02,
    "new-york": 25.01,
    "philadelphia": 24.98,
    "boston": 22.21,
    "dallas": 22.2,
    "toronto": 19.48,
    "kansas-city": 19.43,
    "miami": 19.35,
    "atlanta": 19.35,
    "guadalajara": 11.1,
    "los-angeles": 8.38,
    "seattle": 8.38,
    "vancouver": 8.38,
    "monterrey": 8.36,
    "san-francisco": 8.3,
    "mexico-city": 5.59
  },
  "Inter Path 2": {
    "houston": 25.24,
    "philadelphia": 25.08,
    "new-york": 24.98,
    "dallas": 22.18,
    "boston": 22.06,
    "toronto": 19.53,
    "miami": 19.52,
    "atlanta": 19.52,
    "kansas-city": 19.51,
    "guadalajara": 11.23,
    "san-francisco": 8.33,
    "monterrey": 8.26,
    "los-angeles": 8.21,
    "seattle": 8.21,
    "vancouver": 8.21,
    "mexico-city": 5.65
  },
  "Iran": {
    "san-francisco": 22.45,
    "vancouver": 22.38,
    "houston": 19.12,
    "new-york": 19.03,
    "philadelphia": 19.01,
    "boston": 16.96,
    "dallas": 16.78,
    "guadalajara": 16.29,
    "miami": 14.94,
    "atlanta": 14.94,
    "kansas-city": 14.78,
    "toronto": 14.68,
    "seattle": 14.43,
    "los-angeles": 14.27,
    "monterrey": 14.0,
    "mexico-city": 4.35
  },
  "Ivory Coast": {
    "atlanta": 23.05,
    "san-francisco": 22.82,
    "philadelphia": 18.83,
    "new-york": 18.75,
    "houston": 18.71,
    "boston": 16.65,
    "dallas": 16.63,
    "toronto": 14.69,
    "miami": 14.68,
    "los-angeles": 14.59,
    "vancouver": 14.59,
    "seattle": 14.59,
    "monterrey": 14.55,
    "kansas-city": 14.48,
    "mexico-city": 12.47,
    "guadalajara": 8.36
  },
  "Japan": {
    "vancouver": 22.44,
    "san-francisco": 22.2,
    "philadelphia": 19.1,
    "new-york": 19.08,
    "houston": 18.99,
    "boston": 16.97,
    "dallas": 16.88,
    "guadalajara": 16.29,
    "toronto": 14.84,
    "miami": 14.72,
    "atlanta": 14.72,
    "kansas-city": 14.7,
    "los-angeles": 14.43,
    "seattle": 14.41,
    "monterrey": 14.39,
    "mexico-city": 4.18
  },
  "Jordan": {
    "san-francisco": 27.97,
    "atlanta": 24.23,
    "monterrey": 17.09,
    "los-angeles": 16.98,
    "vancouver": 16.7,
    "seattle": 16.7,
    "philadelphia": 16.61,
    "houston": 16.56,
    "new-york": 16.52,
    "mexico-city": 15.19,
    "boston": 14.6,
    "dallas": 14.6,
    "toronto": 12.93,
    "kansas-city": 12.78,
    "miami": 12.71,
    "guadalajara": 7.26
  },
  "Mexico": {
    "mexico-city": 100.0,
    "guadalajara": 100.0
  },
  "Morocco": {
    "vancouver": 21.6,
    "san-francisco": 21.56,
    "houston": 19.53,
    "philadelphia": 19.28,
    "new-york": 19.22,
    "boston": 16.99,
    "dallas": 16.99,
    "guadalajara": 16.35,
    "miami": 15.1,
    "atlanta": 15.1,
    "kansas-city": 15.01,
    "toronto": 14.9,
    "monterrey": 14.14,
    "los-angeles": 14.01,
    "seattle": 13.98,
    "mexico-city": 4.38
  },
  "Netherlands": {
    "new-york": 26.7,
    "philadelphia": 26.62,
    "houston": 25.85,
    "boston": 22.55,
    "dallas": 22.26,
    "toronto": 20.81,
    "kansas-city": 20.67,
    "miami": 17.63,
    "atlanta": 17.63,
    "guadalajara": 10.11,
    "monterrey": 9.92,
    "los-angeles": 7.53,
    "seattle": 7.53,
    "vancouver": 7.53,
    "san-francisco": 7.43,
    "mexico-city": 4.99
  },
  "New Zealand": {
    "los-angeles": 29.06,
    "toronto": 24.47,
    "atlanta": 24.25,
    "guadalajara": 18.8,
    "san-francisco": 17.3,
    "seattle": 17.22,
    "vancouver": 17.06,
    "houston": 16.13,
    "new-york": 16.1,
    "philadelphia": 16.08,
    "mexico-city": 15.18,
    "dallas": 14.52,
    "boston": 14.41,
    "miami": 12.64,
    "kansas-city": 12.63,
    "monterrey": 5.48
  },
  "Norway": {
    "san-francisco": 23.99,
    "atlanta": 23.21,
    "new-york": 18.37,
    "philadelphia": 18.34,
    "houston": 18.33,
    "boston": 16.35,
    "dallas": 16.1,
    "monterrey": 15.08,
    "los-angeles": 15.02,
    "vancouver": 15.01,
    "seattle": 15.01,
    "toronto": 14.26,
    "miami": 14.2,
    "kansas-city": 14.09,
    "mexico-city": 13.18,
    "guadalajara": 8.14
  },
  "Panama": {
    "new-york": 25.01,
    "philadelphia": 24.97,
    "houston": 24.95,
    "dallas": 22.4,
    "boston": 22.28,
    "kansas-city": 19.5,
    "toronto": 19.47,
    "miami": 19.29,
    "atlanta": 19.29,
    "guadalajara": 11.02,
    "monterrey": 8.46,
    "san-francisco": 8.35,
    "los-angeles": 8.33,
    "seattle": 8.33,
    "vancouver": 8.33,
    "mexico-city": 5.57
  },
  "Paraguay": {
    "los-angeles": 28.76,
    "toronto": 24.31,
    "atlanta": 24.09,
    "guadalajara": 18.73,
    "vancouver": 17.21,
    "san-francisco": 17.11,
    "seattle": 17.02,
    "new-york": 16.34,
    "philadelphia": 16.32,
    "houston": 16.31,
    "mexico-city": 15.16,
    "boston": 14.51,
    "dallas": 14.49,
    "kansas-city": 12.63,
    "miami": 12.57,
    "monterrey": 5.48
  },
  "Portugal": {
    "new-york": 26.76,
    "philadelphia": 26.75,
    "houston": 25.49,
    "boston": 22.7,
    "dallas": 22.55,
    "kansas-city": 20.97,
    "toronto": 20.7,
    "miami": 17.45,
    "atlanta": 17.45,
    "monterrey": 9.95,
    "guadalajara": 9.79,
    "san-francisco": 7.69,
    "los-angeles": 7.54,
    "seattle": 7.54,
    "vancouver": 7.54,
    "mexico-city": 4.84
  },
  "Qatar": {
    "san-francisco": 24.79,
    "atlanta": 23.32,
    "philadelphia": 17.95,
    "new-york": 17.94,
    "houston": 17.79,
    "dallas": 16.2,
    "boston": 15.88,
    "monterrey": 15.66,
    "los-angeles": 15.37,
    "vancouver": 15.28,
    "seattle": 15.28,
    "kansas-city": 14.12,
    "toronto": 14.08,
    "miami": 13.73,
    "mexico-city": 13.41,
    "guadalajara": 7.83
  },
  "Saudi Arabia": {
    "san-francisco": 24.86,
    "atlanta": 23.77,
    "new-york": 17.9,
    "philadelphia": 17.87,
    "houston": 17.66,
    "boston": 16.03,
    "vancouver": 15.65,
    "seattle": 15.65,
    "monterrey": 15.63,
    "dallas": 15.58,
    "los-angeles": 15.42,
    "miami": 14.01,
    "toronto": 13.71,
    "kansas-city": 13.7,
    "mexico-city": 13.61,
    "guadalajara": 7.88
  },
  "Scotland": {
    "san-francisco": 24.33,
    "atlanta": 23.36,
    "houston": 18.3,
    "philadelphia": 18.14,
    "new-york": 18.1,
    "boston": 16.09,
    "dallas": 16.06,
    "los-angeles": 15.25,
    "monterrey": 15.09,
    "vancouver": 14.99,
    "seattle": 14.99,
    "miami": 14.27,
    "kansas-city": 14.12,
    "toronto": 14.03,
    "mexico-city": 13.23,
    "guadalajara": 8.17
  },
  "Senegal": {
    "vancouver": 21.48,
    "san-francisco": 21.4,
    "new-york": 19.49,
    "philadelphia": 19.4,
    "houston": 19.06,
    "boston": 17.49,
    "dallas": 17.02,
    "guadalajara": 16.34,
    "toronto": 15.02,
    "miami": 14.99,
    "atlanta": 14.99,
    "kansas-city": 14.81,
    "monterrey": 14.25,
    "seattle": 14.06,
    "los-angeles": 13.85,
    "mexico-city": 4.26
  },
  "South Africa": {
    "san-francisco": 23.12,
    "atlanta": 23.04,
    "houston": 18.72,
    "new-york": 18.65,
    "philadelphia": 18.64,
    "dallas": 16.69,
    "boston": 16.64,
    "kansas-city": 14.67,
    "miami": 14.67,
    "los-angeles": 14.6,
    "monterrey": 14.57,
    "vancouver": 14.45,
    "seattle": 14.45,
    "toronto": 14.39,
    "mexico-city": 12.58,
    "guadalajara": 8.36
  },
  "South Korea": {
    "san-francisco": 22.5,
    "vancouver": 22.5,
    "houston": 18.84,
    "philadelphia": 18.84,
    "new-york": 18.82,
    "boston": 16.75,
    "guadalajara": 16.74,
    "dallas": 16.72,
    "miami": 14.81,
    "atlanta": 14.81,
    "kansas-city": 14.66,
    "toronto": 14.61,
    "monterrey": 14.51,
    "seattle": 14.48,
    "los-angeles": 14.35,
    "mexico-city": 4.16
  },
  "Spain": {
    "houston": 24.06,
    "philadelphia": 22.9,
    "new-york": 22.84,
    "miami": 21.9,
    "atlanta": 21.9,
    "dallas": 21.78,
    "boston": 21.73,
    "toronto": 17.69,
    "kansas-city": 17.67,
    "guadalajara": 12.54,
    "los-angeles": 9.47,
    "seattle": 9.47,
    "vancouver": 9.47,
    "san-francisco": 9.26,
    "monterrey": 6.28,
    "mexico-city": 6.24
  },
  "Switzerland": {
    "vancouver": 20.41,
    "san-francisco": 20.25,
    "houston": 19.84,
    "philadelphia": 19.78,
    "new-york": 19.77,
    "boston": 17.57,
    "dallas": 17.46,
    "guadalajara": 15.85,
    "miami": 15.53,
    "atlanta": 15.53,
    "kansas-city": 15.34,
    "toronto": 15.31,
    "seattle": 13.63,
    "monterrey": 13.54,
    "los-angeles": 13.5,
    "mexico-city": 4.39
  },
  "Tunisia": {
    "san-francisco": 23.04,
    "vancouver": 23.04,
    "houston": 18.9,
    "philadelphia": 18.8,
    "new-york": 18.73,
    "dallas": 16.8,
    "boston": 16.53,
    "guadalajara": 16.35,
    "kansas-city": 14.78,
    "los-angeles": 14.7,
    "toronto": 14.63,
    "seattle": 14.63,
    "miami": 14.55,
    "atlanta": 14.55,
    "monterrey": 14.35,
    "mexico-city": 4.15
  },
  "UEFA Playoff A": {
    "los-angeles": 31.81,
    "atlanta": 25.15,
    "toronto": 24.7,
    "guadalajara": 20.37,
    "san-francisco": 18.69,
    "vancouver": 18.64,
    "seattle": 18.1,
    "mexico-city": 17.02,
    "houston": 15.1,
    "philadelphia": 14.65,
    "new-york": 14.65,
    "dallas": 13.39,
    "boston": 12.88,
    "kansas-city": 11.72,
    "miami": 11.47,
    "monterrey": 5.13
  },
  "UEFA Playoff B": {
    "los-angeles": 31.95,
    "toronto": 25.09,
    "atlanta": 25.01,
    "guadalajara": 20.11,
    "seattle": 18.6,
    "vancouver": 18.43,
    "san-francisco": 18.31,
    "mexico-city": 16.96,
    "new-york": 14.92,
    "philadelphia": 14.87,
    "houston": 14.72,
    "boston": 13.32,
    "dallas": 13.28,
    "kansas-city": 11.56,
    "miami": 11.36,
    "monterrey": 5.02
  },
  "UEFA Playoff C": {
    "los-angeles": 31.91,
    "atlanta": 25.16,
    "toronto": 25.13,
    "guadalajara": 20.03,
    "seattle": 18.49,
    "vancouver": 18.4,
    "san-francisco": 18.34,
    "mexico-city": 16.68,
    "philadelphia": 15.09,
    "new-york": 15.02,
    "houston": 14.77,
    "boston": 13.38,
    "dallas": 13.12,
    "miami": 11.69,
    "kansas-city": 11.53,
    "monterrey": 4.85
  },
  "UEFA Playoff D": {
    "los-angeles": 32.12,
    "toronto": 25.31,
    "atlanta": 24.66,
    "guadalajara": 19.71,
    "seattle": 18.69,
    "san-francisco": 18.51,
    "vancouver": 18.46,
    "mexico-city": 16.44,
    "new-york": 14.96,
    "philadelphia": 14.95,
    "houston": 14.73,
    "dallas": 13.4,
    "boston": 13.32,
    "kansas-city": 11.69,
    "miami": 11.46,
    "monterrey": 4.96
  },
  "United States": {
    "los-angeles": 100.0,
    "seattle": 100.0
  },
  "Uruguay": {
    "san-francisco": 26.76,
    "vancouver": 26.56,
    "guadalajara": 18.11,
    "new-york": 17.26,
    "philadelphia": 17.25,
    "houston": 16.98,
    "monterrey": 16.21,
    "los-angeles": 16.2,
    "seattle": 15.99,
    "boston": 15.38,
    "dallas": 15.25,
    "kansas-city": 13.4,
    "toronto": 13.35,
    "miami": 13.24,
    "atlanta": 13.24,
    "mexico-city": 3.82
  },
  "Uzbekistan": {
    "san-francisco": 24.83,
    "atlanta": 23.56,
    "houston": 17.98,
    "new-york": 17.84,
    "philadelphia": 17.8,
    "boston": 15.91,
    "dallas": 15.76,
    "monterrey": 15.6,
    "vancouver": 15.53,
    "seattle": 15.53,
    "los-angeles": 15.37,
    "miami": 14.0,
    "kansas-city": 13.81,
    "toronto": 13.75,
    "mexico-city": 13.59,
    "guadalajara": 8.0
  }
}